mcp_tuning/__about__.py
mcp_tuning/__init__.py
mcp_tuning/_api.py
mcp_tuning/_cases.py
mcp_tuning/_exporting.py
mcp_tuning/_inspector.py
mcp_tuning/_mcp_protocol.py
mcp_tuning/_mcp_stdio.py
mcp_tuning/_mock_server.py
mcp_tuning/_rendering.py
mcp_tuning/_utils.py
mcp_tuning/client.py
mcp_tuning/models.py
mcp_tuning/transports/__init__.py
mcp_tuning/transports/_base.py
mcp_tuning/transports/_http.py
mcp_tuning/transports/_sse.py
mcp_tuning/transports/_stdio.py
mcp_tuning-0.1.0.dist-info/METADATA
mcp_tuning-0.1.0.dist-info/WHEEL
mcp_tuning-0.1.0.dist-info/licenses/LICENSE
mcp_tuning-0.1.0.dist-info/RECORD
