Metadata-Version: 2.4
Name: mcp-tuning
Version: 0.1.0
Project-URL: Repository, https://github.com/slime21023/mcp-tuning
License: MIT License
License-File: LICENSE
Classifier: License :: OSI Approved :: MIT License
Requires-Python: >=3.12
Requires-Dist: mcp[cli]>=1.25.0
Provides-Extra: notebook
Requires-Dist: ipykernel>=6.29.0; extra == 'notebook'
Requires-Dist: ipywidgets>=8.1.0; extra == 'notebook'
Requires-Dist: jupyterlab>=4.2.0; extra == 'notebook'
Requires-Dist: rich>=13.7.0; extra == 'notebook'
Provides-Extra: test
Requires-Dist: pytest>=8.0.0; extra == 'test'
